can_raise/__init__.py
can_raise/py.typed
can_raise-0.2.1.dist-info/METADATA
can_raise-0.2.1.dist-info/WHEEL
can_raise-0.2.1.dist-info/licenses/LICENSE
can_raise-0.2.1.dist-info/RECORD
