Metadata-Version: 2.4
Name: can-raise
Version: 0.2.1
Summary: A simple library for decorating functions that can raise exceptions.
Author: EnteryName
License-File: LICENSE
Requires-Python: >=3.10
